hicpeaks/__init__.py
hicpeaks/apa.py
hicpeaks/callers.py
hicpeaks/utilities.py
hicpeaks-0.3.9.data/scripts/apa-analysis
hicpeaks-0.3.9.data/scripts/combine-resolutions
hicpeaks-0.3.9.data/scripts/peak-plot
hicpeaks-0.3.9.data/scripts/pyBHFDR
hicpeaks-0.3.9.data/scripts/pyHICCUPS
hicpeaks-0.3.9.data/scripts/toCooler
hicpeaks-0.3.9.dist-info/LICENSE
hicpeaks-0.3.9.dist-info/METADATA
hicpeaks-0.3.9.dist-info/WHEEL
hicpeaks-0.3.9.dist-info/top_level.txt
hicpeaks-0.3.9.dist-info/RECORD
