Metadata-Version: 2.1
Name: hicpeaks
Version: 0.3.9
Summary: A Python implementation for BH-FDR and HiCCUPS
Home-page: https://github.com/XiaoTaoWang/HiCPeaks/
Author: XiaoTao Wang
Author-email: wangxiaotao686@gmail.com
Keywords: Hi-C chromatin interaction contact loops
Classifier: Programming Language :: Python
Classifier: License :: OSI Approved :: GNU General Public License v3 or later (GPLv3+)
Classifier: Operating System :: POSIX
Classifier: Development Status :: 4 - Beta
Classifier: Intended Audience :: Science/Research
Classifier: Topic :: Scientific/Engineering :: Bio-Informatics
License-File: LICENSE
